grade_change_emailer/__init__.py
grade_change_emailer/example.ini
grade_change_emailer/main.py
grade_change_emailer-0.1.5.dist-info/DESCRIPTION.rst
grade_change_emailer-0.1.5.dist-info/METADATA
grade_change_emailer-0.1.5.dist-info/RECORD
grade_change_emailer-0.1.5.dist-info/WHEEL
grade_change_emailer-0.1.5.dist-info/entry_points.txt
grade_change_emailer-0.1.5.dist-info/metadata.json
grade_change_emailer-0.1.5.dist-info/top_level.txt
