Metadata-Version: 2.0
Name: grade-change-emailer
Version: 0.1.5
Summary: Checks for changes in your grades at the FH Aachen
Home-page: https://github.com/faerbit/grade_change_emailer
Author: Faerbit
Author-email: faerbit at gmail dot com
License: MIT
Platform: UNKNOWN
Classifier: Development Status :: 4 - Beta
Classifier: License :: OSI Approved :: MIT License
Classifier: Environment :: Console
Classifier: Intended Audience :: Developers
Classifier: Intended Audience :: Education
Classifier: Programming Language :: Python :: 3
Classifier: Programming Language :: Python :: 3.3
Classifier: Programming Language :: Python :: 3.4
Classifier: Programming Language :: Python :: 3.5
Classifier: Programming Language :: Python :: 3 :: Only
Classifier: Operating System :: OS Independent
Requires-Dist: appdirs
Requires-Dist: beautifulsoup4
Requires-Dist: requests
